fendi/.env
fendi/.env.enc
fendi/__init__.py
fendi/create.py
fendi/fedi.py
fendi/package_data.dat
fendi/styles/__init__.py
fendi/styles/styles_chat.css
fendi/styles/styles_main.css
fendi/utils/__init__.py
fendi/utils/boxes_linkedin.py
fendi/utils/constants.py
fendi/utils/encrypt.py
fendi/utils/linkedin_to_txt.py
fendi/utils/move_css.py
fendi-0.0.0.13.dist-info/LICENSE.txt
fendi-0.0.0.13.dist-info/METADATA
fendi-0.0.0.13.dist-info/WHEEL
fendi-0.0.0.13.dist-info/entry_points.txt
fendi-0.0.0.13.dist-info/top_level.txt
fendi-0.0.0.13.dist-info/RECORD
