Metadata-Version: 2.1
Name: fendi
Version: 0.0.0.13
Summary: An auto py builder for ChatBots on top of streamlit app's - LLaMa's powered APS
Author-email: Fedi Hamdi <fedihamdi@yahoo.com>
Maintainer-email: Fedi HAMDI <fedihamdi@yahoo.com>, Redouane Kara <kararedouane17@gmail.com>, Dora Debbiche <debbichedora2@gmail.com>, Walid KHIRDINE <khirdine.walid@gmail.com>
License: Copyright (c) 2016 The Python Packaging Authority (PyPA)
Project-URL: Bug Reports, https://github.com/fedihamdi/fendi/issues
Project-URL: Funding, https://donate.pypi.org
Project-URL: Homepage, https://github.com/fedihamdi/fendi
Project-URL: Say Thanks!, https://fedihamdi.netlify.app/
Project-URL: Source, https://github.com/fedihamdi/fendi
Keywords: setuptools,development,genai
Classifier: Development Status :: 3 - Alpha
Classifier: Intended Audience :: Developers
Classifier: Topic :: Software Development :: Build Tools
Classifier: License :: OSI Approved :: MIT License
Classifier: Programming Language :: Python :: 3.10
Classifier: Programming Language :: Python :: 3.11
Requires-Python: >=3.9
License-File: LICENSE.txt
Requires-Dist: peppercorn
Requires-Dist: requests >=2.30.0
Requires-Dist: streamlit ==1.28.2
Requires-Dist: llama-index >=0.8.5
Requires-Dist: llama-cpp-python ==0.1.9
Requires-Dist: nltk ==3.8.1
Requires-Dist: sentence-transformers
Requires-Dist: InstructorEmbedding ==1.0.0
Requires-Dist: huggingface-hub ==0.16.4
Requires-Dist: ibm-watson-machine-learning >=1.0.320
Requires-Dist: langchain
Requires-Dist: pydantic >=1.10.0
Requires-Dist: streamlit-option-menu ==0.1.2
Requires-Dist: streamlit-extras
Requires-Dist: pypdf
Requires-Dist: PyMuPDF
Requires-Dist: argparse >=1.4.0
Provides-Extra: dev
Requires-Dist: check-manifest ; extra == 'dev'
Provides-Extra: test
Requires-Dist: coverage ; extra == 'test'
